aiogram_manager/__main__.py
aiogram_manager/app.py
aiogram_manager/config.py
aiogram_manager/context.py
aiogram_manager/enums.py
aiogram_manager/generator.py
aiogram_manager/templates/__init__.py
aiogram_manager/templates/app/__init__.py
aiogram_manager/templates/app/cookiecutter.json
aiogram_manager/templates/app/{{ cookiecutter.app_name }}/__init__.py
aiogram_manager/templates/app/{{ cookiecutter.app_name }}/callback_factory.py
aiogram_manager/templates/app/{{ cookiecutter.app_name }}/handlers.py
aiogram_manager/templates/app/{{ cookiecutter.app_name }}/models.py
aiogram_manager/templates/app/{{ cookiecutter.app_name }}/services.py
aiogram_manager/templates/app/{{ cookiecutter.app_name }}/states.py
aiogram_manager/templates/project/__init__.py
aiogram_manager/templates/project/cookiecutter.json
aiogram_manager/templates/project/{{ cookiecutter.project_name }}/env.env
aiogram_manager/templates/project/{{ cookiecutter.project_name }}/main.py
aiogram_manager/templates/project/{{ cookiecutter.project_name }}/pyproject.toml
aiogram_manager/templates/project/{{ cookiecutter.project_name }}/readme.md
aiogram_manager/templates/project/{{ cookiecutter.project_name }}/requirements.txt
aiogram_manager/templates/project/{{ cookiecutter.project_name }}/src/__init__.py
aiogram_manager/templates/project/{{ cookiecutter.project_name }}/src/app.py
aiogram_manager/templates/project/{{ cookiecutter.project_name }}/src/apps/__init__.py
aiogram_manager/templates/project/{{ cookiecutter.project_name }}/src/apps/main/__init__.py
aiogram_manager/templates/project/{{ cookiecutter.project_name }}/src/apps/main/handlers.py
aiogram_manager/templates/project/{{ cookiecutter.project_name }}/src/apps/main/keyboards.py
aiogram_manager/templates/project/{{ cookiecutter.project_name }}/src/apps/main/models.py
aiogram_manager/templates/project/{{ cookiecutter.project_name }}/src/core/__init__.py
aiogram_manager/templates/project/{{ cookiecutter.project_name }}/src/core/bot_app.py
aiogram_manager-1.0.0.dist-info/entry_points.txt
aiogram_manager-1.0.0.dist-info/LICENSE.md
aiogram_manager-1.0.0.dist-info/METADATA
aiogram_manager-1.0.0.dist-info/WHEEL
aiogram_manager-1.0.0.dist-info/RECORD
